{"cameraMode":{"drawMode":0,"name":"Shaded","section":"Shading Mode"},"sceneLighting":true,"audioPlay":false,"sceneViewState":{"m_AlwaysRefresh":false,"showFog":true,"showSkybox":true,"showFlares":true,"showImageEffects":true,"showParticleSystems":true,"showVisualEffectGraphs":true,"m_FxEnabled":true},"in2DMode":false,"pivot":{"x":-3.7282421588897707,"y":4.133735656738281,"z":-7.055510520935059},"rotation":{"x":-0.2176208198070526,"y":-0.09760566800832749,"z":0.021878506988286973,"w":-0.9708954691886902},"size":5.875844478607178,"orthographic":false}